LICENSE
django_enhanced_settings/__init__.py
django_enhanced_settings/read_types.py
django_enhanced_settings/settings.py
django_enhanced_settings-0.2.4.dist-info/LICENSE
django_enhanced_settings-0.2.4.dist-info/WHEEL
django_enhanced_settings-0.2.4.dist-info/METADATA
django_enhanced_settings-0.2.4.dist-info/RECORD
